backgroundking/__init__.py
backgroundking/threadmanager.py
backgroundking-0.1.4.dist-info/licenses/LICENSE
backgroundking-0.1.4.dist-info/METADATA
backgroundking-0.1.4.dist-info/WHEEL
backgroundking-0.1.4.dist-info/top_level.txt
backgroundking-0.1.4.dist-info/RECORD
